{
  "이재명": [
    {
      "ticker": "000660",
      "name": "SK하이닉스",
      "relation": "이재명 대통령의 '반도체 산업 육성' 공약의 핵심 수혜주로, 메모리 반도체 분야의 대표 기업입니다.",
      "confidence": "high",
      "category": "policy"
    },
    {
      "ticker": "240810",
      "name": "원익IPS",
      "relation": "이재명 대통령의 '반도체 산업 육성' 정책 추진 시, 반도체 증착 장비 등 핵심 장비 공급사로서 수혜가 기대됩니다.",
      "confidence": "medium",
      "category": "policy"
    },
    {
      "ticker": "281820",
      "name": "케이씨텍",
      "relation": "반도체 공정용 소재(CMP 슬러리) 및 장비(세정 장비)를 공급하는 기업으로, '반도체 산업 육성' 정책에 따른 수요 증가가 예상됩니다.",
      "confidence": "medium",
      "category": "policy"
    },
    {
      "ticker": "373220",
      "name": "LG에너지솔루션",
      "relation": "이재명 대통령의 '전기차 산업 육성' 공약의 최대 수혜주 중 하나로, 글로벌 2차전지 시장을 선도하는 기업입니다.",
      "confidence": "high",
      "category": "policy"
    },
    {
      "ticker": "003670",
      "name": "포스코퓨처엠",
      "relation": "전기차 배터리의 핵심 소재인 양극재 및 음극재를 생산하는 기업으로, '전기차 산업 육성' 정책 추진 시 수혜가 예상됩니다.",
      "confidence": "high",
      "category": "policy"
    },
    {
      "ticker": "247540",
      "name": "에코프로비엠",
      "relation": "2차전지 양극재 분야의 선두 기업으로, '전기차 산업 육성' 정책에 따라 전기차 배터리 수요 증가의 직접적인 수혜가 기대됩니다.",
      "confidence": "high",
      "category": "policy"
    },
    {
      "ticker": "204320",
      "name": "만도",
      "relation": "전기차 및 자율주행 핵심 부품을 개발 및 공급하는 기업으로, '전기차 산업 육성' 정책에 힘입어 성장 동력을 확보할 것으로 예상됩니다.",
      "confidence": "medium",
      "category": "policy"
    },
    {
      "ticker": "035600",
      "name": "KG이니시스",
      "relation": "국내 1위 온라인 결제 서비스(PG) 기업으로, '기본소득 정책 추진' 시 디지털 바우처 또는 간편결제 방식으로 지급될 경우 관련 결제액 증가가 기대됩니다.",
      "confidence": "medium",
      "category": "policy"
    }
  ],
  "정원오": [
    {
      "ticker": "014790",
      "name": "한라",
      "relation": "본사가 정원오 후보의 정치적 기반인 성동구에 위치해 있습니다. 건설 및 주택 사업을 영위하며, 성동구청장으로서 추진했던 도시재생 및 주거 관련 정책의 수혜주로 분류될 수 있습니다.",
      "confidence": "high",
      "category": "region"
    },
    {
      "ticker": "071670",
      "name": "에이테크솔루션",
      "relation": "본사가 성동구 성수동에 위치해 있습니다. 정원오 후보가 성수동 도시재생 및 소셜벤처 육성을 강조했던 만큼, 성수동에 기반을 둔 기술 관련 기업으로서 주목받을 가능성이 있습니다.",
      "confidence": "medium",
      "category": "region"
    },
    {
      "ticker": "006360",
      "name": "GS건설",
      "relation": "정원오 후보가 서울시장 후보로서 주택 공급, 도시재생, SOC 확충 등 건설/부동산 관련 공약을 발표할 경우, 서울 지역에 다수의 아파트 브랜드(자이) 및 재개발/재건축 실적을 보유한 대형 건설사로서 수혜가 기대됩니다.",
      "confidence": "medium",
      "category": "policy"
    },
    {
      "ticker": "000210",
      "name": "DL이앤씨",
      "relation": "대형 건설사로서 서울시의 주택 공급, 환경 개선, 도시 인프라 등 정원오 후보의 정책 방향과 관련된 사업에서 수주 기회가 확대될 수 있습니다. 과거 대림건설 시절부터 서울 내 주요 개발 프로젝트에 참여해 왔습니다.",
      "confidence": "medium",
      "category": "policy"
    },
    {
      "ticker": "011780",
      "name": "금호석유화학",
      "relation": "정원오 후보의 출신 고향인 여수시에 대규모 생산 공장을 보유하고 있는 대표적인 여수 기반 기업입니다. 후보가 지역 경제 활성화 공약 등을 발표할 경우 지역 관련 테마주로 주목받을 수 있습니다.",
      "confidence": "medium",
      "category": "region"
    },
    {
      "ticker": "011170",
      "name": "롯데케미칼",
      "relation": "금호석유화학과 마찬가지로 정원오 후보의 고향인 여수 국가산업단지에 대규모 생산 시설을 운영하고 있습니다. 여수 출신 정치인 테마주로 분류될 가능성이 있습니다.",
      "confidence": "medium",
      "category": "region"
    },
    {
      "ticker": "041510",
      "name": "에스엠엔터테인먼트",
      "relation": "과거 성동구 성수동에 본사 사옥을 두었고, 현재도 성수동 지역의 문화 콘텐츠 산업 활성화에 기여하고 있습니다. 정원오 후보의 성수동 도시재생 정책 중 문화예술 콘텐츠 산업 육성 공약과 연결될 수 있습니다.",
      "confidence": "low",
      "category": "region"
    },
    {
      "ticker": "007660",
      "name": "이수페타시스",
      "relation": "본사가 서울 성동구에 위치하며, 고부가가치 전자부품(PCB) 제조업을 영위합니다. 정원오 후보가 강조한 소셜벤처 및 미래 산업 육성 정책과 간접적으로 연결될 수 있는 성동구 기반의 기술 기업입니다.",
      "confidence": "low",
      "category": "region"
    }
  ],
  "김동연": [
    {
      "ticker": "000660",
      "name": "SK하이닉스",
      "relation": "경기 용인 반도체 클러스터에 입주 예정인 대규모 기업으로, 김동연 지사의 반도체 클러스터 조성 및 육성 정책의 직접적인 수혜가 기대됨.",
      "confidence": "high",
      "category": "policy"
    },
    {
      "ticker": "240810",
      "name": "원익IPS",
      "relation": "반도체 전공정 장비 제조업체로, 경기도 내 주요 반도체 생산시설에 장비를 공급하며 김동연 지사의 반도체 클러스터 정책 확대 시 동반 성장이 기대됨.",
      "confidence": "medium",
      "category": "policy"
    },
    {
      "ticker": "005290",
      "name": "동진쎄미켐",
      "relation": "반도체 공정용 화학재료 생산 기업으로, 경기도 내 주요 반도체 클러스터 기업들과 긴밀한 관계를 맺고 있어 김동연 지사의 반도체 산업 육성 정책의 수혜주로 분류될 수 있음.",
      "confidence": "medium",
      "category": "policy"
    },
    {
      "ticker": "000720",
      "name": "현대건설",
      "relation": "GTX 등 광역교통망 확충 사업에 참여할 수 있는 국내 대표적인 건설사로, 김동연 지사의 GTX 추진 공약의 직접적인 수혜가 기대됨.",
      "confidence": "high",
      "category": "policy"
    },
    {
      "ticker": "047040",
      "name": "대우건설",
      "relation": "GTX 노선 연장 및 신설 등 경기도 내 SOC 확충 사업 참여 가능성이 높은 건설사로, 김동연 지사의 교통 인프라 정책 관련 테마주로 분류될 수 있음.",
      "confidence": "high",
      "category": "policy"
    },
    {
      "ticker": "058730",
      "name": "다스코",
      "relation": "도로시설물 제조 및 설치 전문 기업으로, GTX 등 교통 인프라 확충 시 필요한 부대시설물 공급 확대가 기대되어 김동연 지사의 SOC 공약 관련주로 부각될 수 있음.",
      "confidence": "medium",
      "category": "policy"
    },
    {
      "ticker": "035420",
      "name": "네이버",
      "relation": "본사가 경기도 성남시에 위치한 국내 대표 IT 기업으로, 김동연 지사의 경기도 지역 경제 활성화 및 첨단 산업 육성 정책의 간접 수혜를 기대할 수 있음.",
      "confidence": "medium",
      "category": "region"
    },
    {
      "ticker": "035720",
      "name": "카카오",
      "relation": "본사가 경기도 성남시에 위치한 국내 대표 플랫폼 기업으로, 김동연 지사의 경기도 내 IT 산업 지원 및 지역 경제 활성화 정책의 수혜주로 간주될 수 있음.",
      "confidence": "medium",
      "category": "region"
    },
    {
      "ticker": "030200",
      "name": "KT",
      "relation": "본사가 경기도 성남시에 위치한 국내 대표 통신 기업으로, 경기도의 디지털 전환 및 스마트시티 구축 등 김동연 지사의 미래 산업 육성 정책과 연관될 수 있음.",
      "confidence": "medium",
      "category": "region"
    }
  ],
  "추미애": [
    {
      "ticker": "074600",
      "name": "원익QnC",
      "relation": "경기도는 세계적인 반도체 산업의 중심지입니다. 원익QnC는 오산 등 경기도에 주요 생산 시설을 두고 반도체 산업의 핵심 소재인 쿼츠웨어를 공급하며, 경기지사 후보로서 지역 핵심 산업 육성 공약과 연관성이 높습니다.",
      "confidence": "high",
      "category": "policy, region"
    },
    {
      "ticker": "029460",
      "name": "케이씨텍",
      "relation": "반도체 및 디스플레이 장비와 소재를 생산하는 기업으로, 경기도 안성시에 본사와 공장을 두고 있습니다. 경기도의 대표적인 첨단 제조업 기업으로서, 경기지사 후보의 지역 경제 활성화 및 첨단 산업 육성 정책과 밀접하게 연관됩니다.",
      "confidence": "high",
      "category": "policy, region"
    },
    {
      "ticker": "005290",
      "name": "동진쎄미켐",
      "relation": "반도체 및 디스플레이용 재료(포토레지스트 등)를 개발하고 생산하는 기업으로, 화성 등 경기도에 주요 사업장을 운영하고 있습니다. 경기도의 첨단 산업 생태계에 중요한 역할을 하며, 경기지사 후보의 지역 산업 육성 공약의 수혜를 입을 가능성이 있습니다.",
      "confidence": "high",
      "category": "policy, region"
    },
    {
      "ticker": "000240",
      "name": "삼천리",
      "relation": "경기도 수원, 용인, 화성 등 주요 지역에 도시가스를 공급하는 핵심 인프라 기업입니다. 경기지사 후보의 지역 주민 생활 안정 및 인프라 확충 정책과 직접적인 연관성을 가지며, 경기도 내 사업 비중이 매우 높습니다.",
      "confidence": "high",
      "category": "region, policy"
    },
    {
      "ticker": "009450",
      "name": "경동나비엔",
      "relation": "보일러 및 온수기 등 주택 설비 제조업체로, 경기도 평택시에 본사를 두고 있습니다. 경기도 내 중요한 제조업 기반을 형성하며, 지역 경제 기여 및 주택 관련 정책 방향에 따라 영향을 받을 수 있습니다.",
      "confidence": "medium",
      "category": "region"
    },
    {
      "ticker": "086960",
      "name": "한컴MDS",
      "relation": "IoT, 임베디드 소프트웨어, 스마트 팩토리 등 첨단 IT 솔루션을 제공하는 기업으로, 경기도 성남 판교에 본사를 두고 있습니다. 판교는 경기도의 첨단 IT 및 4차 산업혁명 거점으로, 경기지사 후보의 미래 산업 육성 및 스마트 시티 구현 정책과 연관성이 높습니다.",
      "confidence": "medium",
      "category": "region, policy"
    },
    {
      "ticker": "000620",
      "name": "LS ELECTRIC",
      "relation": "전력기기, 자동화, 스마트 에너지 솔루션 등을 제공하는 기업으로, 경기도 안양에 R&D 센터 및 사업장을 운영하고 있습니다. 더불어민주당의 친환경·스마트 인프라 정책 기조와 일치하며, 경기지사 후보가 추진할 스마트 에너지 및 산업 자동화 관련 정책의 수혜를 기대할 수 있습니다.",
      "confidence": "medium",
      "category": "policy, region"
    }
  ]
}